MANIFEST.in
setup.py
egen111222_MyProject.egg-info/PKG-INFO
egen111222_MyProject.egg-info/SOURCES.txt
egen111222_MyProject.egg-info/dependency_links.txt
egen111222_MyProject.egg-info/top_level.txt
module1/__init__.py
module1/first_module.py
module2/__init__.py
module2/dsa.py