Metadata-Version: 2.1
Name: egen111222-MyProject
Version: 1.0
Summary: Tmp project
Home-page: https://www.google.com/
Author: Kirill
Author-email: egen13@ukr.net
License: UNKNOWN
Platform: UNKNOWN
